setup.py
loopyTools/__init__.py
loopyTools.egg-info/PKG-INFO
loopyTools.egg-info/SOURCES.txt
loopyTools.egg-info/dependency_links.txt
loopyTools.egg-info/requires.txt
loopyTools.egg-info/top_level.txt