Metadata-Version: 1.2
Name: loopyTools
Version: 0.0.1
Summary: Install all packages that I need for ML and import them in my way.
Home-page: UNKNOWN
Author: loopyme
Author-email: peter@mail.loopy.tech
Maintainer: loopyme
Maintainer-email: peter@mail.loopy.tech
License: MIT License
Platform: all
